Metadata-Version: 2.1
Name: odoo14-addon-base_rest
Version: 14.0.4.8.5
Summary: Develop your own high level REST APIs for Odoo thanks to this addon.
Home-page: https://github.com/OCA/rest-framework
Author: ACSONE SA/NV, Odoo Community Association (OCA)
Author-email: support@odoo-community.org
License: LGPL-3
Classifier: Programming Language :: Python
Classifier: Framework :: Odoo
Classifier: Framework :: Odoo :: 14.0
Classifier: License :: OSI Approved :: GNU Lesser General Public License v3 (LGPLv3)
Classifier: Development Status :: 4 - Beta
Requires-Python: >=3.6
Requires-Dist: apispec
Requires-Dist: cerberus
Requires-Dist: odoo14-addon-component
Requires-Dist: odoo<14.1dev,>=14.0a
Requires-Dist: parse-accept-language
Requires-Dist: pyquerystring
